cimonitor/__init__.py
cimonitor/__main__.py
cimonitor/cli.py
cimonitor/fetcher.py
cimonitor/log_parser.py
cimonitor/services.py
cimonitor-0.1.4.dist-info/METADATA
cimonitor-0.1.4.dist-info/WHEEL
cimonitor-0.1.4.dist-info/entry_points.txt
cimonitor-0.1.4.dist-info/licenses/LICENSE
cimonitor-0.1.4.dist-info/RECORD
